laguardia/__init__.py
laguardia/cli.py
laguardia/engine.py
laguardia-0.2.0.dist-info/METADATA
laguardia-0.2.0.dist-info/WHEEL
laguardia-0.2.0.dist-info/entry_points.txt
laguardia-0.2.0.dist-info/top_level.txt
laguardia-0.2.0.dist-info/RECORD
