Metadata-Version: 2.4
Name: laguardia
Version: 0.2.0
Summary: LaGuardia - Lightweight Policy-as-Code for Terraform/OpenTofu
Author: Senora.dev OSS
Requires-Python: >=3.9
Requires-Dist: PyYAML>=6.0
